bloxroute_cli/README.compare-tx-feeds.md
bloxroute_cli/__init__.py
bloxroute_cli/compare_block_feeds.py
bloxroute_cli/compare_eth_on_block_feed.py
bloxroute_cli/compare_tx_feeds.py
bloxroute_cli/compare_tx_feeds_gateways.py
bloxroute_cli/compare_tx_feeds_time_diff.py
bloxroute_cli/compare_tx_speed.py
bloxroute_cli/main.py
bloxroute_cli/provider/__init__.py
bloxroute_cli/provider/ipc_provider.py
bxcommon/__init__.py
bxcommon/common_init_tasks.py
bxcommon/common_opts.py
bxcommon/constants.py
bxcommon/exceptions.py
bxcommon/log_messages.py
bxcommon/node_runner.py
bxcommon/models/__init__.py
bxcommon/models/authenticated_peer_info.py
bxcommon/models/bdn_account_model_base.py
bxcommon/models/bdn_msg_quota_service_entity_type.py
bxcommon/models/bdn_service_model_base.py
bxcommon/models/bdn_service_model_config_base.py
bxcommon/models/bdn_service_type.py
bxcommon/models/blockchain_network_environment.py
bxcommon/models/blockchain_network_model.py
bxcommon/models/blockchain_network_type.py
bxcommon/models/blockchain_peer_info.py
bxcommon/models/blockchain_protocol.py
bxcommon/models/broadcast_message_type.py
bxcommon/models/entity_type_model.py
bxcommon/models/gateway_settings_model.py
bxcommon/models/node_event_model.py
bxcommon/models/node_model.py
bxcommon/models/node_type.py
bxcommon/models/notification_code.py
bxcommon/models/notification_code_formatting.py
bxcommon/models/outbound_peer_model.py
bxcommon/models/platform_provider.py
bxcommon/models/quota_type_model.py
bxcommon/models/serializable_flag.py
bxcommon/models/serializeable_enum.py
bxcommon/models/time_interval_type.py
bxcommon/models/transaction_flag.py
bxcommon/models/transaction_info.py
bxcommon/models/transaction_key.py
bxcommon/models/tx_blockchain_status.py
bxcommon/models/tx_validation_status.py
bxcommon/models/config/__init__.py
bxcommon/models/config/abstract_config_model.py
bxcommon/models/config/cron_config_model.py
bxcommon/models/config/log_config_model.py
bloxroute_cli-1.109.9.dist-info/LICENSE
bloxroute_cli-1.109.9.dist-info/METADATA
bloxroute_cli-1.109.9.dist-info/WHEEL
bloxroute_cli-1.109.9.dist-info/entry_points.txt
bloxroute_cli-1.109.9.dist-info/top_level.txt
bloxroute_cli-1.109.9.dist-info/RECORD
