Metadata-Version: 2.1
Name: bloxroute-cli
Version: 1.109.9
Summary: bloXroute CLI
Home-page: https://bloxroute.com
Author: bloXroute Labs Inc.
Author-email: support@bloxroute.com
License: MIT
Platform: UNKNOWN
Classifier: Programming Language :: Python :: 3.6
Classifier: Programming Language :: Python :: 3.7
Classifier: Development Status :: 4 - Beta
Classifier: License :: OSI Approved :: MIT License
Requires-Python: ~=3.6
Requires-Dist: aiohttp (==3.7.3)
Requires-Dist: websockets (==8.1)
Requires-Dist: pyhumps (==1.6.1)
Requires-Dist: web3 (<=5.13.1,>=5.11.1)
Requires-Dist: orjson (==3.4.6)
Requires-Dist: dataclasses (==0.6)
